interstat/__init__.py
interstat/__main__.py
interstat/filters.py
interstat/formats.py
interstat/formatters.py
interstat/templates/log.html
interstat/templates/style.css
interstat/templates/message/action.html
interstat/templates/message/join.html
interstat/templates/message/kick.html
interstat/templates/message/misc.html
interstat/templates/message/mode.html
interstat/templates/message/nick.html
interstat/templates/message/notice.html
interstat/templates/message/part.html
interstat/templates/message/privmsg.html
interstat/templates/message/quit.html
interstat/templates/message/topic.html
interstat/test/__init__.py
interstat/test/test_formatters.py
interstat-0.2.2.dist-info/DESCRIPTION.rst
interstat-0.2.2.dist-info/entry_points.txt
interstat-0.2.2.dist-info/METADATA
interstat-0.2.2.dist-info/metadata.json
interstat-0.2.2.dist-info/RECORD
interstat-0.2.2.dist-info/top_level.txt
interstat-0.2.2.dist-info/WHEEL
