Metadata-Version: 2.0
Name: interstat
Version: 0.2.2
Summary: An HTML formatter for IRC log files
Home-page: https://github.com/kxz/interstat
Author: Kevin Xiwei Zheng
Author-email: blankplacement+interstat@gmail.com
License: X11
Keywords: irc html log
Platform: UNKNOWN
Classifier: Development Status :: 3 - Alpha
Classifier: Environment :: Console
Classifier: Intended Audience :: System Administrators
Classifier: License :: OSI Approved :: MIT License
Classifier: Operating System :: OS Independent
Classifier: Programming Language :: Python :: 2
Classifier: Programming Language :: Python :: 2.7
Classifier: Programming Language :: Python :: 3
Classifier: Programming Language :: Python :: 3.4
Classifier: Topic :: Communications :: Chat :: Internet Relay Chat
Classifier: Topic :: Text Processing :: Markup :: HTML
Requires-Dist: future
Requires-Dist: Jinja2
